certum/__init__.py
certum/__version__.py
certum/decipher.py
certum/dsl.py
certum/error.py
certum/exception.py
certum/private.py
certum/rule/generic/abstract.py
certum/rule/generic/apply.py
certum/rule/generic/foreach.py
certum/rule/generic/forsome.py
certum/rule/shared/equals.py
certum/rule/shared/has_length_of.py
certum/rule/shared/has_unique_elements.py
certum/rule/shared/is_empty.py
certum/rule/shared/is_instance_of.py
certum/rule/shared/is_not_empty.py
certum/rule/shared/is_one_of.py
certum/strategy/abstract.py
certum/strategy/filtering/abstract.py
certum/strategy/filtering/first.py
certum/strategy/filtering/no.py
certum/strategy/filtering/thunk.py
certum/strategy/printing/abstract.py
certum/strategy/printing/grouped.py
certum/strategy/printing/simple.py
certum/strategy/sorting/abstract.py
certum/strategy/sorting/alphabetical.py
certum/strategy/sorting/no.py
certum/validator.py
certum-1.0a1.dist-info/WHEEL
certum-1.0a1.dist-info/METADATA
certum-1.0a1.dist-info/RECORD
