Metadata-Version: 2.1
Name: certum
Version: 1.0a1
Summary: A dictionary validation library based on partial, composable and expressive rules.
Home-page: https://github.com/dylandoamaral/certum
Author: dylandoamaral
Author-email: do.amaral.dylan@gmail.com
Requires-Python: >=3.6,<4
Classifier: Programming Language :: Python :: 3
Classifier: Programming Language :: Python :: 3.6
Classifier: Programming Language :: Python :: 3.7
Classifier: Programming Language :: Python :: 3.8
Classifier: Programming Language :: Python :: 3.9
Project-URL: Repository, https://github.com/dylandoamaral/certum
